tests/__init__.py
tests/test_create_wqx_document.py
wqxlib/Document.py
wqxlib/Header.py
wqxlib/ImportConfiguration.py
wqxlib/Payload.py
wqxlib/Submission.py
wqxlib/WQXActivity.py
wqxlib/WQXAttachedBinaryObject.py
wqxlib/WQXElectronicAddress.py
wqxlib/WQXMonitoringLocation.py
wqxlib/WQXOrganizationAddress.py
wqxlib/WQXOrganizationDescription.py
wqxlib/WQXResult.py
wqxlib/WQXSample.py
wqxlib/WQXSubmission.py
wqxlib/WQXTelephonic.py
wqxlib/__init__.py
wqxlib/__main__.py
wqxlib/exceptions.py
wqxlib/wqx_v3_0/Activity.py
wqxlib/wqx_v3_0/ActivityDescription.py
wqxlib/wqx_v3_0/ActivityGroup.py
wqxlib/wqx_v3_0/ActivityLocation.py
wqxlib/wqx_v3_0/ActivityMetric.py
wqxlib/wqx_v3_0/ActivityMetricType.py
wqxlib/wqx_v3_0/AlternateMonitoringLocationIdentity.py
wqxlib/wqx_v3_0/AquiferInformation.py
wqxlib/wqx_v3_0/AttachedBinaryObject.py
wqxlib/wqx_v3_0/BibliographicReference.py
wqxlib/wqx_v3_0/BiologicalActivityDescription.py
wqxlib/wqx_v3_0/BiologicalHabitatCollectionInformation.py
wqxlib/wqx_v3_0/BiologicalHabitatIndex.py
wqxlib/wqx_v3_0/BiologicalResultDescription.py
wqxlib/wqx_v3_0/CollectionEffort.py
wqxlib/wqx_v3_0/ComparableAnalyticalMethod.py
wqxlib/wqx_v3_0/DataQualityIndicator.py
wqxlib/wqx_v3_0/DetectionQuantitationLimit.py
wqxlib/wqx_v3_0/ElectronicAddress.py
wqxlib/wqx_v3_0/Entity_Update_Identifiers.py
wqxlib/wqx_v3_0/FrequencyClassInformation.py
wqxlib/wqx_v3_0/HorizontalAccuracyMeasure.py
wqxlib/wqx_v3_0/IndexType.py
wqxlib/wqx_v3_0/LabSamplePreparation.py
wqxlib/wqx_v3_0/Measure.py
wqxlib/wqx_v3_0/MeasureCompact.py
wqxlib/wqx_v3_0/MonitoringLocation.py
wqxlib/wqx_v3_0/MonitoringLocationGeospatial.py
wqxlib/wqx_v3_0/MonitoringLocationIdentity.py
wqxlib/wqx_v3_0/NetInformation.py
wqxlib/wqx_v3_0/Organization.py
wqxlib/wqx_v3_0/OrganizationAddress.py
wqxlib/wqx_v3_0/OrganizationDescription.py
wqxlib/wqx_v3_0/Organization_Delete.py
wqxlib/wqx_v3_0/Project.py
wqxlib/wqx_v3_0/ProjectMonitoringLocationWeighting.py
wqxlib/wqx_v3_0/ReferenceMethod.py
wqxlib-3.0.0.6.0.dist-info/LICENSE
wqxlib-3.0.0.6.0.dist-info/METADATA
wqxlib-3.0.0.6.0.dist-info/WHEEL
wqxlib-3.0.0.6.0.dist-info/top_level.txt
wqxlib-3.0.0.6.0.dist-info/RECORD
