Metadata-Version: 2.1
Name: wqxlib
Version: 3.0.0.6.0
Summary: A library to create files for the EPA's WQX service.
Home-page: https://github.com/FlippingBinary/wqxlib/tree/main/wqxlib-python
Author: Jon Musselwhite
Author-email: JMusselwhite@wvstateu.edu
License: UNKNOWN
Platform: UNKNOWN
Classifier: Development Status :: 4 - Beta
Classifier: Intended Audience :: Developers
Classifier: Intended Audience :: Science/Research
Classifier: Programming Language :: Python :: 3
Classifier: License :: OSI Approved :: MIT License
Classifier: Natural Language :: English
Classifier: Operating System :: OS Independent
Classifier: Topic :: Scientific/Engineering
Classifier: Topic :: Scientific/Engineering :: Hydrology
Classifier: Topic :: Software Development :: Libraries
Classifier: Topic :: Software Development :: Libraries :: Python Modules
Requires-Python: >=3.6
License-File: LICENSE
Requires-Dist: requests (>=2.25.0)
Requires-Dist: yattag (>=1.14.0)
Requires-Dist: rfc3986 (>=1.4.0)
Requires-Dist: wheel (>=0.36.2)
